LICENSE.txt
MANIFEST.in
README.md
setup.py
examples/call_c_from_python/README.md
examples/call_c_from_python/bar.py
examples/call_c_from_python/c.c
examples/call_c_from_python/pin.conf
examples/call_python_from_c/README.md
examples/call_python_from_c/c.c
examples/call_python_from_c/foo.py
examples/call_python_from_c/pin.conf
pybrm/__init__.py
pybrm/_version.py
pybrm/constants.py
pybrm/pybrm.py
pybrm.egg-info/PKG-INFO
pybrm.egg-info/SOURCES.txt
pybrm.egg-info/dependency_links.txt
pybrm.egg-info/top_level.txt
src/pybrm.c
tests/pin.conf
tests/tests.py
tests/pin_conf_test/pin.conf