Metadata-Version: 2.1
Name: pybrm
Version: 1.0.0
Summary: A Python library for Oracle BRM
Home-page: https://github.com/mkmoisen/pybrm
Author: Matthew Moisen
Author-email: mmoisen@cisco.com
License: MIT
Project-URL: Documentation, https://github.com/mkmoisen/pybrm
Project-URL: Source, https://github.com/mkmoisen/pybrm
Keywords: brm
Platform: UNKNOWN
Classifier: Intended Audience :: Developers
Classifier: Intended Audience :: Telecommunications Industry
Classifier: License :: OSI Approved :: MIT License
Classifier: Programming Language :: Python
Classifier: Programming Language :: Python :: 3
Classifier: Programming Language :: Python :: 3.6
Classifier: Programming Language :: Python :: 3.7
Classifier: Programming Language :: Python :: Implementation :: CPython
Classifier: Programming Language :: C
Classifier: Operating System :: POSIX :: Linux
Classifier: Natural Language :: English
Requires-Python: >=3.6
